fitgirl/__init__.py
fitgirl/client/__init__.py
fitgirl/client/_api.py
fitgirl/client/_base.py
fitgirl/client/_browse.py
fitgirl/client/_special.py
fitgirl/client/_urls.py
fitgirl/client/client.py
fitgirl/client/rss.py
fitgirl/exceptions.py
fitgirl/models/__init__.py
fitgirl/models/api.py
fitgirl/models/donation.py
fitgirl/models/pages.py
fitgirl/models/repack.py
fitgirl/models/taxonomy.py
fitgirl/models/torrent.py
fitgirl/parsers/__init__.py
fitgirl/parsers/_utils.py
fitgirl/parsers/api.py
fitgirl/parsers/listing.py
fitgirl/parsers/repack.py
fitgirl/parsers/special.py
fitgirl/py.typed
fitgirl/transport.py
fitgirl/utils/__init__.py
fitgirl/utils/magnets.py
fitgirl/utils/tracker.py
fitgirl-0.2.0.dist-info/WHEEL
fitgirl-0.2.0.dist-info/METADATA
fitgirl-0.2.0.dist-info/RECORD
