Metadata-Version: 2.3
Name: fitgirl
Version: 0.2.0
Summary: Add your description here
Author: xsyncio
Requires-Dist: curl-cffi>=0.14.0
Requires-Dist: msgspec>=0.20.0
Requires-Dist: selectolax>=0.4.6
Requires-Dist: playwright>=1.49.1
Requires-Python: >=3.13
